README.md
pflogf.py
setup.py
pflogf.egg-info/PKG-INFO
pflogf.egg-info/SOURCES.txt
pflogf.egg-info/dependency_links.txt
pflogf.egg-info/entry_points.txt
pflogf.egg-info/requires.txt
pflogf.egg-info/top_level.txt