Metadata-Version: 2.1
Name: pflogf
Version: 0.0.3
Summary: Logging formatter for fnndsc/pf* family, inspired by pfmisc.debug
Home-page: https://github.com/FNNDSC/pflogf
Author: Jennings Zhang
Author-email: Jennings.Zhang@childrens.harvard.edu
License: MIT
Keywords: logging color
Platform: UNKNOWN
Classifier: Environment :: Console
Classifier: License :: OSI Approved :: MIT License
Requires-Python: >=3.6
